setup.py
GitTornado.egg-info/PKG-INFO
GitTornado.egg-info/SOURCES.txt
GitTornado.egg-info/dependency_links.txt
GitTornado.egg-info/entry_points.txt
GitTornado.egg-info/requires.txt
GitTornado.egg-info/top_level.txt
GitTornado.egg-info/zip-safe
gittornado/__init__.py
gittornado/iowrapper.py
gittornado/server.py
gittornado/util.py