Metadata-Version: 1.0
Name: GitTornado
Version: 0.1.0
Summary: Tornado-based implementation of the git HTTP protocol supporting gzip and chunked transfers
Home-page: https://github.com/mensi/gittornado
Author: Manuel Stocker
Author-email: mensi@mensi.ch
License: GPL
Keywords: git http
Platform: UNKNOWN
Classifier: Development Status :: 2 - Pre-Alpha
Classifier: Environment :: Web Environment
Classifier: Intended Audience :: Developers
Classifier: License :: OSI Approved :: GNU General Public License (GPL)
Classifier: Operating System :: OS Independent
Classifier: Programming Language :: Python
